waterquality/__init__.py
waterquality/common/DataCleaning.py
waterquality/common/__init__.py
waterquality/eemdlstm/EEMD_LSTM_ZY.py
waterquality/eemdlstm/Predict_ZY.py
waterquality/eemdlstm/__init__.py
waterquality/eemdlstm/base/EEMD_LSTM_BASE.py
waterquality/eemdlstm/base/__init__.py
waterquality/loaddata/ParserHuiZhouExcelData.py
waterquality/loaddata/Parser_jilonghe_ExcelData.py
waterquality/loaddata/__init__.py
waterquality/normal/RelativeAnalyse.py
waterquality/normal/__init__.py
waterquality/normal/base/__init__.py
analysetool-0.0.4.dist-info/METADATA
analysetool-0.0.4.dist-info/WHEEL
analysetool-0.0.4.dist-info/top_level.txt
analysetool-0.0.4.dist-info/RECORD
