Metadata-Version: 2.1
Name: analysetool
Version: 0.0.4
Requires-Dist: requests
Requires-Dist: importlib-metadata ; python_version < "3.8"
